modseccfg/__init__.py
modseccfg/__main__.py
modseccfg/advise.py
modseccfg/crsoptions.py
modseccfg/editor.py
modseccfg/icons.py
modseccfg/logs.py
modseccfg/mainwindow.py
modseccfg/modify.py
modseccfg/msc_pyrewrite.py
modseccfg/recipe.py
modseccfg/ruleinfo.py
modseccfg/secoptions.py
modseccfg/utils.py
modseccfg/vhosts.py
modseccfg/writer.py
modseccfg/data/__init__.py
modseccfg/data/common_false_positives.log
modseccfg/install/__init__.py
modseccfg/install/get_SecHttpBlKey.local.sh
modseccfg/install/modsec-flameeyes_2020.06.13_all.deb
modseccfg/install/python3-logfmt1_0.5-2_all.deb
modseccfg/install/setup_preconf_scheme.py
modseccfg/install/update_logfmt.py
modseccfg/scripts/__init__.py
modseccfg/scripts/accesslog_last_24h.sh
modseccfg/scripts/accesslog_request_timing.sh
modseccfg/scripts/aliases.sh
modseccfg/scripts/arbigraph.sh
modseccfg/scripts/fix_dateformat.py
modseccfg/scripts/lastrequestsummary.sh
modseccfg/scripts/lnav.sh
modseccfg/scripts/modsec-positive-stats.rb
modseccfg/scripts/modsec-rulereport-new.rb
modseccfg/scripts/modsec-rulereport.rb
modseccfg/scripts/parse-apache-logs.rb
modseccfg/scripts/rulereportnew.sh
modseccfg/scripts/rulereportold.sh
modseccfg-0.7.3.post2.data/data/man/man1/modseccfg.1
modseccfg-0.7.3.post2.dist-info/LICENSE
modseccfg-0.7.3.post2.dist-info/METADATA
modseccfg-0.7.3.post2.dist-info/WHEEL
modseccfg-0.7.3.post2.dist-info/entry_points.txt
modseccfg-0.7.3.post2.dist-info/top_level.txt
modseccfg-0.7.3.post2.dist-info/RECORD
