Metadata-Version: 2.1
Name: modseccfg
Version: 0.7.3.post2
Summary: Editor to tame mod_security rulesets
Home-page: https://fossil.include-once.org/modseccfg/
License: Apache-2.0
Project-URL: Faq, https://fossil.include-once.org/modseccfg/doc/trunk/FAQ.md
Keywords: modsecurity mod-security mod_security apache config desktop sshfs
Classifier: Topic :: Desktop Environment :: K Desktop Environment (KDE)
Classifier: Topic :: Internet :: WWW/HTTP
Classifier: Topic :: Internet :: WWW/HTTP :: HTTP Servers
Classifier: Topic :: Security
Classifier: Topic :: Software Development :: Libraries :: Python Modules
Classifier: Topic :: System :: Boot :: Init
Requires-Python: >= 3.6
License-File: LICENSE
Requires-Dist: pysimplegui (>=3.0)
Requires-Dist: pluginconf (>=0.7.3)
Requires-Dist: appdirs (>=1.3)
Requires-Dist: logfmt1 (>=0.4)
Provides-Extra: all
Requires-Dist: msc-pyparser (>=1.1.1) ; extra == 'all'
